{
  "type": "Compass Connections",
  "version": {
    "$numberInt": "1"
  },
  "connections": [
    {
      "id": "a00f9b0b-9e27-4ccb-8e81-2d11958700cd",
      "lastUsed": {
        "$date": {
          "$numberLong": "1759203213109"
        }
      },
      "favorite": {
        "name": "portal50-2"
      },
      "savedConnectionType": "recent",
      "connectionOptions": {
        "connectionString": "mongodb://localhost:27017/",
        "oidc": {
          "serializedState": "eyJvaWRjUGx1Z2luU3RhdGVWZXJzaW9uIjoxLCJzdGF0ZSI6W119"
        }
      }
    }
  ]
}